{
  "db_name": "PostgreSQL",
  "query": "\n        WITH RECURSIVE category_tree AS (\n            -- Base case: the requested category\n            SELECT id FROM categories WHERE id = $1 AND user_id = $2\n            UNION ALL\n            -- Recursive step: find all children of the categories in the tree\n            SELECT ch.category_id\n            FROM category_hierarchy ch\n            INNER JOIN category_tree ct ON ch.parent_id = ct.id\n        )\n        SELECT\n            t.id AS transaction_id, t.description, t.amount, t.created_at AS transaction_created_at,\n            c.id AS category_id, c.name, c.created_at AS category_created_at,\n            ch.parent_id as \"parent_id?\"\n        FROM transactions t\n        JOIN categories c ON t.category_id = c.id\n        LEFT JOIN category_hierarchy ch ON c.id = ch.category_id\n        WHERE c.id IN (SELECT id FROM category_tree)\n        AND t.user_id = $2\n        ORDER BY t.created_at DESC\n        ",
  "describe": {
    "columns": [
      {
        "ordinal": 0,
        "name": "transaction_id",
        "type_info": "Int4"
      },
      {
        "ordinal": 1,
        "name": "description",
        "type_info": "Text"
      },
      {
        "ordinal": 2,
        "name": "amount",
        "type_info": "Numeric"
      },
      {
        "ordinal": 3,
        "name": "transaction_created_at",
        "type_info": "Timestamptz"
      },
      {
        "ordinal": 4,
        "name": "category_id",
        "type_info": "Int4"
      },
      {
        "ordinal": 5,
        "name": "name",
        "type_info": "Text"
      },
      {
        "ordinal": 6,
        "name": "category_created_at",
        "type_info": "Timestamptz"
      },
      {
        "ordinal": 7,
        "name": "parent_id?",
        "type_info": "Int4"
      }
    ],
    "parameters": {
      "Left": [
        "Int4",
        "Uuid"
      ]
    },
    "nullable": [
      false,
      false,
      false,
      false,
      false,
      false,
      false,
      false
    ]
  },
  "hash": "2abc64fd480c093ca24bb7fd9f6a9502c0eb568cdb1d1e4658f45cafa2a1802b"
}
