{
  "db_name": "PostgreSQL",
  "query": "\n        UPDATE categories SET name = $1 WHERE id = $2 AND user_id = $3\n        RETURNING id, name, created_at\n        ",
  "describe": {
    "columns": [
      {
        "ordinal": 0,
        "name": "id",
        "type_info": "Int4"
      },
      {
        "ordinal": 1,
        "name": "name",
        "type_info": "Text"
      },
      {
        "ordinal": 2,
        "name": "created_at",
        "type_info": "Timestamptz"
      }
    ],
    "parameters": {
      "Left": [
        "Text",
        "Int4",
        "Uuid"
      ]
    },
    "nullable": [
      false,
      false,
      false
    ]
  },
  "hash": "02d5935821dde5e79a3c3ae3e75d25b22acf39b8b728d9028600bef22dc4020e"
}
